{
    "meta": {
        "id": "good-tveets-4-26-2016",
        "title": "Good TVeets 4/27/2016",
        "date": 1461789275
    },
    "tweets": [
        {
            "url": "https://twitter.com/DamienFahey/status/720266252850044929",
            "author_name": "Damien Fahey",
            "author_url": "https://twitter.com/DamienFahey",
            "html": "<blockquote class=\"twitter-tweet\"><p lang=\"en\" dir=\"ltr\">Can we get that football doctor to study the brains of adults who stand with signs outside of the Today show?</p>&mdash; Damien Fahey (@DamienFahey) <a href=\"https://twitter.com/DamienFahey/status/720266252850044929?ref_src=twsrc%5Etfw\">April 13, 2016</a></blockquote>\n<script async src=\"https://platform.twitter.com/widgets.js\" charset=\"utf-8\"></script>\n",
            "width": 550,
            "height": null,
            "type": "rich",
            "cache_age": "3153600000",
            "provider_name": "Twitter",
            "provider_url": "https://twitter.com",
            "version": "1.0"
        },
        {
            "url": "https://twitter.com/kalebhorton/status/724700546599251968",
            "author_name": "Kaleb “Christmas” Horton",
            "author_url": "https://twitter.com/kalebhorton",
            "html": "<blockquote class=\"twitter-tweet\"><p lang=\"en\" dir=\"ltr\">Hell is a real place. Specifically, it&#39;s a series of real places. Very specifically, it&#39;s any computer Piers Morgan can viably use to write.</p>&mdash; Kaleb “Christmas” Horton (@kalebhorton) <a href=\"https://twitter.com/kalebhorton/status/724700546599251968?ref_src=twsrc%5Etfw\">April 25, 2016</a></blockquote>\n<script async src=\"https://platform.twitter.com/widgets.js\" charset=\"utf-8\"></script>\n",
            "width": 550,
            "height": null,
            "type": "rich",
            "cache_age": "3153600000",
            "provider_name": "Twitter",
            "provider_url": "https://twitter.com",
            "version": "1.0"
        },
        {
            "url": "https://twitter.com/BenjaminJS/status/724733343221186560",
            "author_name": "Ben Siemon",
            "author_url": "https://twitter.com/BenjaminJS",
            "html": "<blockquote class=\"twitter-tweet\"><p lang=\"en\" dir=\"ltr\">If you saw Piers Morgan 3 times in the bathroom mirror, he&#39;ll appear. Unless there&#39;s a strong black woman nearby. Then he&#39;ll blog instead.</p>&mdash; Ben Siemon (@BenjaminJS) <a href=\"https://twitter.com/BenjaminJS/status/724733343221186560?ref_src=twsrc%5Etfw\">April 25, 2016</a></blockquote>\n<script async src=\"https://platform.twitter.com/widgets.js\" charset=\"utf-8\"></script>\n",
            "width": 550,
            "height": null,
            "type": "rich",
            "cache_age": "3153600000",
            "provider_name": "Twitter",
            "provider_url": "https://twitter.com",
            "version": "1.0"
        },
        {
            "url": "https://twitter.com/JeffreySconce/status/724762560109498369",
            "author_name": "Jeffrey Sconce",
            "author_url": "https://twitter.com/JeffreySconce",
            "html": "<blockquote class=\"twitter-tweet\"><p lang=\"en\" dir=\"ltr\">Clickbait tells me Piers Morgan has some thoughts on the new Beyoncé album.  Nice try, merchants of fury.</p>&mdash; Jeffrey Sconce (@JeffreySconce) <a href=\"https://twitter.com/JeffreySconce/status/724762560109498369?ref_src=twsrc%5Etfw\">April 26, 2016</a></blockquote>\n<script async src=\"https://platform.twitter.com/widgets.js\" charset=\"utf-8\"></script>\n",
            "width": 550,
            "height": null,
            "type": "rich",
            "cache_age": "3153600000",
            "provider_name": "Twitter",
            "provider_url": "https://twitter.com",
            "version": "1.0"
        },
        {
            "url": "https://twitter.com/extranapkins/status/724743245717225472",
            "author_name": "''Steve''",
            "author_url": "https://twitter.com/extranapkins",
            "html": "<blockquote class=\"twitter-tweet\"><p lang=\"en\" dir=\"ltr\">White People Telling White People Not To Write Beyoncé Thinkpieces Need To Step Back. Beyoncé Thinkpieces Are A Vital Part Of White Culture</p>&mdash; &#39;&#39;Steve&#39;&#39; (@extranapkins) <a href=\"https://twitter.com/extranapkins/status/724743245717225472?ref_src=twsrc%5Etfw\">April 25, 2016</a></blockquote>\n<script async src=\"https://platform.twitter.com/widgets.js\" charset=\"utf-8\"></script>\n",
            "width": 550,
            "height": null,
            "type": "rich",
            "cache_age": "3153600000",
            "provider_name": "Twitter",
            "provider_url": "https://twitter.com",
            "version": "1.0"
        },
        {
            "url": "https://twitter.com/notjustmovies/status/725121561158623233",
            "author_name": "Jake Cole",
            "author_url": "https://twitter.com/notjustmovies",
            "html": "<blockquote class=\"twitter-tweet\"><p lang=\"en\" dir=\"ltr\">&quot;Watch James Corden&#39;s FLAWLESS Lemonade paro-&quot; *goes back in time and kills Tim Berners-Lee to stop the Internet from ever happening*</p>&mdash; Jake Cole (@notjustmovies) <a href=\"https://twitter.com/notjustmovies/status/725121561158623233?ref_src=twsrc%5Etfw\">April 27, 2016</a></blockquote>\n<script async src=\"https://platform.twitter.com/widgets.js\" charset=\"utf-8\"></script>\n",
            "width": 550,
            "height": null,
            "type": "rich",
            "cache_age": "3153600000",
            "provider_name": "Twitter",
            "provider_url": "https://twitter.com",
            "version": "1.0"
        },
        {
            "url": "https://twitter.com/SamuelAAdams/status/724756332834856960",
            "author_name": "Sam Adams",
            "author_url": "https://twitter.com/SamuelAAdams",
            "html": "<blockquote class=\"twitter-tweet\"><p lang=\"en\" dir=\"ltr\">Crazy Ex-Girlfriend’s first season continues to stubbornly be over.</p>&mdash; Sam Adams (@SamuelAAdams) <a href=\"https://twitter.com/SamuelAAdams/status/724756332834856960?ref_src=twsrc%5Etfw\">April 26, 2016</a></blockquote>\n<script async src=\"https://platform.twitter.com/widgets.js\" charset=\"utf-8\"></script>\n",
            "width": 550,
            "height": null,
            "type": "rich",
            "cache_age": "3153600000",
            "provider_name": "Twitter",
            "provider_url": "https://twitter.com",
            "version": "1.0"
        },
        {
            "url": "https://twitter.com/LouisPeitzman/status/724784636832944128",
            "author_name": "Louis Peitzman",
            "author_url": "https://twitter.com/LouisPeitzman",
            "html": "<blockquote class=\"twitter-tweet\"><p lang=\"en\" dir=\"ltr\">Let&#39;s be mature enough to admit that Zach Florrick got hot.</p>&mdash; Louis Peitzman (@LouisPeitzman) <a href=\"https://twitter.com/LouisPeitzman/status/724784636832944128?ref_src=twsrc%5Etfw\">April 26, 2016</a></blockquote>\n<script async src=\"https://platform.twitter.com/widgets.js\" charset=\"utf-8\"></script>\n",
            "width": 550,
            "height": null,
            "type": "rich",
            "cache_age": "3153600000",
            "provider_name": "Twitter",
            "provider_url": "https://twitter.com",
            "version": "1.0"
        },
        {
            "url": "https://twitter.com/LisaMcIntire/status/724784903267569664",
            "author_name": "Lisa McIntire",
            "author_url": "https://twitter.com/LisaMcIntire",
            "html": "<blockquote class=\"twitter-tweet\"><p lang=\"en\" dir=\"ltr\">Want to feel old? This is the baby from the Nirvana album cover. <a href=\"https://t.co/UesxYbUUbd\">pic.twitter.com/UesxYbUUbd</a></p>&mdash; Lisa McIntire (@LisaMcIntire) <a href=\"https://twitter.com/LisaMcIntire/status/724784903267569664?ref_src=twsrc%5Etfw\">April 26, 2016</a></blockquote>\n<script async src=\"https://platform.twitter.com/widgets.js\" charset=\"utf-8\"></script>\n",
            "width": 550,
            "height": null,
            "type": "rich",
            "cache_age": "3153600000",
            "provider_name": "Twitter",
            "provider_url": "https://twitter.com",
            "version": "1.0"
        },
        {
            "url": "https://twitter.com/stephbrown/status/724807871469244417",
            "author_name": "Stephanie Brown",
            "author_url": "https://twitter.com/stephbrown",
            "html": "<blockquote class=\"twitter-tweet\"><p lang=\"en\" dir=\"ltr\">I&#39;ve internalized TV story structure to the point where my greatest anxiety sets in when I&#39;m most happy.</p>&mdash; Stephanie Brown (@stephbrown) <a href=\"https://twitter.com/stephbrown/status/724807871469244417?ref_src=twsrc%5Etfw\">April 26, 2016</a></blockquote>\n<script async src=\"https://platform.twitter.com/widgets.js\" charset=\"utf-8\"></script>\n",
            "width": 550,
            "height": null,
            "type": "rich",
            "cache_age": "3153600000",
            "provider_name": "Twitter",
            "provider_url": "https://twitter.com",
            "version": "1.0"
        },
        {
            "url": "https://twitter.com/stephbrown/status/724807989916372992",
            "author_name": "Stephanie Brown",
            "author_url": "https://twitter.com/stephbrown",
            "html": "<blockquote class=\"twitter-tweet\"><p lang=\"en\" dir=\"ltr\">This tweet brought to you by Jane The Virgin and foreshadowing</p>&mdash; Stephanie Brown (@stephbrown) <a href=\"https://twitter.com/stephbrown/status/724807989916372992?ref_src=twsrc%5Etfw\">April 26, 2016</a></blockquote>\n<script async src=\"https://platform.twitter.com/widgets.js\" charset=\"utf-8\"></script>\n",
            "width": 550,
            "height": null,
            "type": "rich",
            "cache_age": "3153600000",
            "provider_name": "Twitter",
            "provider_url": "https://twitter.com",
            "version": "1.0"
        },
        {
            "url": "https://twitter.com/TVKel/status/725141821358260224",
            "author_name": "Kel \"Jingle Jangle Bells\" K.",
            "author_url": "https://twitter.com/TVKel",
            "html": "<blockquote class=\"twitter-tweet\"><p lang=\"en\" dir=\"ltr\">Happy characters!!! Which means something really shitty is about to happen! DAMN YOU TV!! <a href=\"https://twitter.com/hashtag/DemAgents?src=hash&amp;ref_src=twsrc%5Etfw\">#DemAgents</a> <a href=\"https://twitter.com/hashtag/AgentsofSHIELD?src=hash&amp;ref_src=twsrc%5Etfw\">#AgentsofSHIELD</a></p>&mdash; Kel &quot;Jingle Jangle Bells&quot; K. (@TVKel) <a href=\"https://twitter.com/TVKel/status/725141821358260224?ref_src=twsrc%5Etfw\">April 27, 2016</a></blockquote>\n<script async src=\"https://platform.twitter.com/widgets.js\" charset=\"utf-8\"></script>\n",
            "width": 550,
            "height": null,
            "type": "rich",
            "cache_age": "3153600000",
            "provider_name": "Twitter",
            "provider_url": "https://twitter.com",
            "version": "1.0"
        },
        {
            "url": "https://twitter.com/noelrk/status/724946896515682304",
            "author_name": "Noel Kirkpatrick",
            "author_url": "https://twitter.com/noelrk",
            "html": "<blockquote class=\"twitter-tweet\"><p lang=\"en\" dir=\"ltr\">Did you all learn nothing from Netflix queues? You&#39;re going to load up your FilmStruck list w/lots of films but only watch Mad Max 8 times.</p>&mdash; Noel Kirkpatrick (@noelrk) <a href=\"https://twitter.com/noelrk/status/724946896515682304?ref_src=twsrc%5Etfw\">April 26, 2016</a></blockquote>\n<script async src=\"https://platform.twitter.com/widgets.js\" charset=\"utf-8\"></script>\n",
            "width": 550,
            "height": null,
            "type": "rich",
            "cache_age": "3153600000",
            "provider_name": "Twitter",
            "provider_url": "https://twitter.com",
            "version": "1.0"
        },
        {
            "url": "https://twitter.com/TVMcGee/status/724657181979738113",
            "author_name": "Ryan McGee",
            "author_url": "https://twitter.com/TVMcGee",
            "html": "<blockquote class=\"twitter-tweet\"><p lang=\"en\" dir=\"ltr\">The 4,732 Actors in <a href=\"https://twitter.com/hashtag/TwinPeaks?src=hash&amp;ref_src=twsrc%5Etfw\">#TwinPeaks</a>, Definitively Ranked</p>&mdash; Ryan McGee (@TVMcGee) <a href=\"https://twitter.com/TVMcGee/status/724657181979738113?ref_src=twsrc%5Etfw\">April 25, 2016</a></blockquote>\n<script async src=\"https://platform.twitter.com/widgets.js\" charset=\"utf-8\"></script>\n",
            "width": 550,
            "height": null,
            "type": "rich",
            "cache_age": "3153600000",
            "provider_name": "Twitter",
            "provider_url": "https://twitter.com",
            "version": "1.0"
        },
        {
            "url": "https://twitter.com/bortlb/status/724657443012108294",
            "author_name": "Laurence \"Laura Dern\" Barber",
            "author_url": "https://twitter.com/bortlb",
            "html": "<blockquote class=\"twitter-tweet\"><p lang=\"en\" dir=\"ltr\">Congrats to everyone who entered the “Which Gossip Girl actor will turn up in a Twin Peaks revival?” pool &amp; chose Jessica Szohr.</p>&mdash; Laurence &quot;Laura Dern&quot; Barber (@bortlb) <a href=\"https://twitter.com/bortlb/status/724657443012108294?ref_src=twsrc%5Etfw\">April 25, 2016</a></blockquote>\n<script async src=\"https://platform.twitter.com/widgets.js\" charset=\"utf-8\"></script>\n",
            "width": 550,
            "height": null,
            "type": "rich",
            "cache_age": "3153600000",
            "provider_name": "Twitter",
            "provider_url": "https://twitter.com",
            "version": "1.0"
        },
        {
            "url": "https://twitter.com/TheFienPrint/status/725000106039234561",
            "author_name": "Daniel Fienberg",
            "author_url": "https://twitter.com/TheFienPrint",
            "html": "<blockquote class=\"twitter-tweet\"><p lang=\"en\" dir=\"ltr\">Check back tomorrow when David Lynch and Showtime release the names of all of the journalists who will be writing about <a href=\"https://twitter.com/hashtag/TwinPeaks?src=hash&amp;ref_src=twsrc%5Etfw\">#TwinPeaks</a>.</p>&mdash; Daniel Fienberg (@TheFienPrint) <a href=\"https://twitter.com/TheFienPrint/status/725000106039234561?ref_src=twsrc%5Etfw\">April 26, 2016</a></blockquote>\n<script async src=\"https://platform.twitter.com/widgets.js\" charset=\"utf-8\"></script>\n",
            "width": 550,
            "height": null,
            "type": "rich",
            "cache_age": "3153600000",
            "provider_name": "Twitter",
            "provider_url": "https://twitter.com",
            "version": "1.0"
        },
        {
            "url": "https://twitter.com/BobbyRiversTV/status/724940246798991360",
            "author_name": "Bobby Rivers",
            "author_url": "https://twitter.com/BobbyRiversTV",
            "html": "<blockquote class=\"twitter-tweet\"><p lang=\"en\" dir=\"ltr\">Michael Strahan &amp; Kelly Ripa should enter today looking like George &amp; Martha in WHO&#39;S AFRAID OF VIRGINIA WOOLF? <a href=\"https://t.co/lRlIMOANan\">pic.twitter.com/lRlIMOANan</a></p>&mdash; Bobby Rivers (@BobbyRiversTV) <a href=\"https://twitter.com/BobbyRiversTV/status/724940246798991360?ref_src=twsrc%5Etfw\">April 26, 2016</a></blockquote>\n<script async src=\"https://platform.twitter.com/widgets.js\" charset=\"utf-8\"></script>\n",
            "width": 550,
            "height": null,
            "type": "rich",
            "cache_age": "3153600000",
            "provider_name": "Twitter",
            "provider_url": "https://twitter.com",
            "version": "1.0"
        },
        {
            "url": "https://twitter.com/Schwindter/status/724949897582133249",
            "author_name": "Oriana Schwindt",
            "author_url": "https://twitter.com/Schwindter",
            "html": "<blockquote class=\"twitter-tweet\"><p lang=\"en\" dir=\"ltr\">Kelly Ripa just pulled off one of the more elegant high-wire acts: Didn’t let ABC off the hook, but also made clear she’s a team player.</p>&mdash; Oriana Schwindt (@Schwindter) <a href=\"https://twitter.com/Schwindter/status/724949897582133249?ref_src=twsrc%5Etfw\">April 26, 2016</a></blockquote>\n<script async src=\"https://platform.twitter.com/widgets.js\" charset=\"utf-8\"></script>\n",
            "width": 550,
            "height": null,
            "type": "rich",
            "cache_age": "3153600000",
            "provider_name": "Twitter",
            "provider_url": "https://twitter.com",
            "version": "1.0"
        },
        {
            "url": "https://twitter.com/pkafka/status/724948123911639040",
            "author_name": "Peter Kafka",
            "author_url": "https://twitter.com/pkafka",
            "html": "<blockquote class=\"twitter-tweet\"><p lang=\"en\" dir=\"ltr\">daytime talkshow viewing is not normally a thing in my twitter</p>&mdash; Peter Kafka (@pkafka) <a href=\"https://twitter.com/pkafka/status/724948123911639040?ref_src=twsrc%5Etfw\">April 26, 2016</a></blockquote>\n<script async src=\"https://platform.twitter.com/widgets.js\" charset=\"utf-8\"></script>\n",
            "width": 550,
            "height": null,
            "type": "rich",
            "cache_age": "3153600000",
            "provider_name": "Twitter",
            "provider_url": "https://twitter.com",
            "version": "1.0"
        },
        {
            "url": "https://twitter.com/nprmonkeysee/status/724981177401114625",
            "author_name": "Linda Holmes",
            "author_url": "https://twitter.com/nprmonkeysee",
            "html": "<blockquote class=\"twitter-tweet\"><p lang=\"en\" dir=\"ltr\">Look, if they didn&#39;t want me to watch THE PRICE IS RIGHT at my desk, they wouldn&#39;t have given me a TV.</p>&mdash; Linda Holmes (@nprmonkeysee) <a href=\"https://twitter.com/nprmonkeysee/status/724981177401114625?ref_src=twsrc%5Etfw\">April 26, 2016</a></blockquote>\n<script async src=\"https://platform.twitter.com/widgets.js\" charset=\"utf-8\"></script>\n",
            "width": 550,
            "height": null,
            "type": "rich",
            "cache_age": "3153600000",
            "provider_name": "Twitter",
            "provider_url": "https://twitter.com",
            "version": "1.0"
        },
        {
            "url": "https://twitter.com/PhilipMichaels/status/725113630895820801",
            "author_name": "Philip Michaels",
            "author_url": "https://twitter.com/PhilipMichaels",
            "html": "<blockquote class=\"twitter-tweet\"><p lang=\"en\" dir=\"ltr\">When Skip Bayless joins Cowherd, Whitlock and Travis at Fox Sports, can we just rename the network Monster Island and be done with it?</p>&mdash; Philip Michaels (@PhilipMichaels) <a href=\"https://twitter.com/PhilipMichaels/status/725113630895820801?ref_src=twsrc%5Etfw\">April 27, 2016</a></blockquote>\n<script async src=\"https://platform.twitter.com/widgets.js\" charset=\"utf-8\"></script>\n",
            "width": 550,
            "height": null,
            "type": "rich",
            "cache_age": "3153600000",
            "provider_name": "Twitter",
            "provider_url": "https://twitter.com",
            "version": "1.0"
        },
        {
            "url": "https://twitter.com/mquirion/status/725151253915942912",
            "author_name": "Matt Quirion",
            "author_url": "https://twitter.com/mquirion",
            "html": "<blockquote class=\"twitter-tweet\"><p lang=\"en\" dir=\"ltr\">You have to log in to HBO Go every night, or it’ll forget your Fios credentials and then the world ends. It’s like the Numbers in Lost.</p>&mdash; Matt Quirion (@mquirion) <a href=\"https://twitter.com/mquirion/status/725151253915942912?ref_src=twsrc%5Etfw\">April 27, 2016</a></blockquote>\n<script async src=\"https://platform.twitter.com/widgets.js\" charset=\"utf-8\"></script>\n",
            "width": 550,
            "height": null,
            "type": "rich",
            "cache_age": "3153600000",
            "provider_name": "Twitter",
            "provider_url": "https://twitter.com",
            "version": "1.0"
        },
        {
            "url": "https://twitter.com/Serrae/status/725160366582300672",
            "author_name": "melissa miller",
            "author_url": "https://twitter.com/Serrae",
            "html": "<blockquote class=\"twitter-tweet\"><p lang=\"en\" dir=\"ltr\">Watching the <a href=\"https://twitter.com/hashtag/BetterCallSaul?src=hash&amp;ref_src=twsrc%5Etfw\">#BetterCallSaul</a> finale. I would watch a show that was just Jonathan Banks and Jim Beaver talking about guns.</p>&mdash; melissa miller (@Serrae) <a href=\"https://twitter.com/Serrae/status/725160366582300672?ref_src=twsrc%5Etfw\">April 27, 2016</a></blockquote>\n<script async src=\"https://platform.twitter.com/widgets.js\" charset=\"utf-8\"></script>\n",
            "width": 550,
            "height": null,
            "type": "rich",
            "cache_age": "3153600000",
            "provider_name": "Twitter",
            "provider_url": "https://twitter.com",
            "version": "1.0"
        },
        {
            "url": "https://twitter.com/JarettSays/status/725414974407868416",
            "author_name": "Jarett Wieselman",
            "author_url": "https://twitter.com/JarettSays",
            "html": "<blockquote class=\"twitter-tweet\"><p lang=\"en\" dir=\"ltr\">&quot;Hell On Wheels&quot; ran for five seasons on AMC. There is nothing you&#39;re incapable of doing!</p>&mdash; Jarett Wieselman (@JarettSays) <a href=\"https://twitter.com/JarettSays/status/725414974407868416?ref_src=twsrc%5Etfw\">April 27, 2016</a></blockquote>\n<script async src=\"https://platform.twitter.com/widgets.js\" charset=\"utf-8\"></script>\n",
            "width": 550,
            "height": null,
            "type": "rich",
            "cache_age": "3153600000",
            "provider_name": "Twitter",
            "provider_url": "https://twitter.com",
            "version": "1.0"
        },
        {
            "url": "https://twitter.com/pourmecoffee/status/725136844833300480",
            "author_name": "pourmecoffee",
            "author_url": "https://twitter.com/pourmecoffee",
            "html": "<blockquote class=\"twitter-tweet\"><p lang=\"en\" dir=\"ltr\">My brother just texted me that guy from The Apprentice will be GOP nominee for president and he&#39;s right. Turn on your TV, this is nuts.</p>&mdash; pourmecoffee (@pourmecoffee) <a href=\"https://twitter.com/pourmecoffee/status/725136844833300480?ref_src=twsrc%5Etfw\">April 27, 2016</a></blockquote>\n<script async src=\"https://platform.twitter.com/widgets.js\" charset=\"utf-8\"></script>\n",
            "width": 550,
            "height": null,
            "type": "rich",
            "cache_age": "3153600000",
            "provider_name": "Twitter",
            "provider_url": "https://twitter.com",
            "version": "1.0"
        },
        {
            "url": "https://twitter.com/Carrasquillo/status/725142316185427968",
            "author_name": "Adrian Carrasquillo",
            "author_url": "https://twitter.com/Carrasquillo",
            "html": "<blockquote class=\"twitter-tweet\"><p lang=\"en\" dir=\"ltr\">Christie: I&#39;m happy. No seriously. You won&#39;t catch a memeable sad face, you monsters. <a href=\"https://t.co/hqVoQB8BT5\">pic.twitter.com/hqVoQB8BT5</a></p>&mdash; Adrian Carrasquillo (@Carrasquillo) <a href=\"https://twitter.com/Carrasquillo/status/725142316185427968?ref_src=twsrc%5Etfw\">April 27, 2016</a></blockquote>\n<script async src=\"https://platform.twitter.com/widgets.js\" charset=\"utf-8\"></script>\n",
            "width": 550,
            "height": null,
            "type": "rich",
            "cache_age": "3153600000",
            "provider_name": "Twitter",
            "provider_url": "https://twitter.com",
            "version": "1.0"
        },
        {
            "url": "https://twitter.com/jonlovett/status/725142864754302978",
            "author_name": "Jon Lovett",
            "author_url": "https://twitter.com/jonlovett",
            "html": "<blockquote class=\"twitter-tweet\"><p lang=\"en\" dir=\"ltr\">Trump hires the best people. Not the best advance staffers, delegate wranglers, audio techs, press aides, but besides that the best the peop</p>&mdash; Jon Lovett (@jonlovett) <a href=\"https://twitter.com/jonlovett/status/725142864754302978?ref_src=twsrc%5Etfw\">April 27, 2016</a></blockquote>\n<script async src=\"https://platform.twitter.com/widgets.js\" charset=\"utf-8\"></script>\n",
            "width": 550,
            "height": null,
            "type": "rich",
            "cache_age": "3153600000",
            "provider_name": "Twitter",
            "provider_url": "https://twitter.com",
            "version": "1.0"
        },
        {
            "url": "https://twitter.com/pbump/status/725142547841073152",
            "author_name": "Philip Bump",
            "author_url": "https://twitter.com/pbump",
            "html": "<blockquote class=\"twitter-tweet\"><p lang=\"und\" dir=\"ltr\"><a href=\"https://t.co/BSUA6ukG1z\">pic.twitter.com/BSUA6ukG1z</a></p>&mdash; Philip Bump (@pbump) <a href=\"https://twitter.com/pbump/status/725142547841073152?ref_src=twsrc%5Etfw\">April 27, 2016</a></blockquote>\n<script async src=\"https://platform.twitter.com/widgets.js\" charset=\"utf-8\"></script>\n",
            "width": 550,
            "height": null,
            "type": "rich",
            "cache_age": "3153600000",
            "provider_name": "Twitter",
            "provider_url": "https://twitter.com",
            "version": "1.0"
        },
        {
            "url": "https://twitter.com/kalebhorton/status/725150932384681984",
            "author_name": "Kaleb “Christmas” Horton",
            "author_url": "https://twitter.com/kalebhorton",
            "html": "<blockquote class=\"twitter-tweet\"><p lang=\"en\" dir=\"ltr\">My official position on the Donald Trump victory speech is that Super Karate Monkey Death Car is Stephen Root&#39;s best Newsradio episode.</p>&mdash; Kaleb “Christmas” Horton (@kalebhorton) <a href=\"https://twitter.com/kalebhorton/status/725150932384681984?ref_src=twsrc%5Etfw\">April 27, 2016</a></blockquote>\n<script async src=\"https://platform.twitter.com/widgets.js\" charset=\"utf-8\"></script>\n",
            "width": 550,
            "height": null,
            "type": "rich",
            "cache_age": "3153600000",
            "provider_name": "Twitter",
            "provider_url": "https://twitter.com",
            "version": "1.0"
        },
        {
            "url": "https://twitter.com/Anthony/status/725158883124252672",
            "author_name": "Anthony De Rosa 🗽",
            "author_url": "https://twitter.com/Anthony",
            "html": "<blockquote class=\"twitter-tweet\"><p lang=\"en\" dir=\"ltr\">The modern Republican Party is basically 4chan.</p>&mdash; Anthony De Rosa 🗽 (@Anthony) <a href=\"https://twitter.com/Anthony/status/725158883124252672?ref_src=twsrc%5Etfw\">April 27, 2016</a></blockquote>\n<script async src=\"https://platform.twitter.com/widgets.js\" charset=\"utf-8\"></script>\n",
            "width": 550,
            "height": null,
            "type": "rich",
            "cache_age": "3153600000",
            "provider_name": "Twitter",
            "provider_url": "https://twitter.com",
            "version": "1.0"
        },
        {
            "url": "https://twitter.com/annetdonahue/status/725293227394383872",
            "author_name": "Anne T. Donahue",
            "author_url": "https://twitter.com/annetdonahue",
            "html": "<blockquote class=\"twitter-tweet\"><p lang=\"en\" dir=\"ltr\">If there&#39;s an upside to Trump&#39;s candidacy it&#39;s that it tells kids that anybody can run for president. Like, ANYbody. Anyone. Any. Person.</p>&mdash; Anne T. Donahue (@annetdonahue) <a href=\"https://twitter.com/annetdonahue/status/725293227394383872?ref_src=twsrc%5Etfw\">April 27, 2016</a></blockquote>\n<script async src=\"https://platform.twitter.com/widgets.js\" charset=\"utf-8\"></script>\n",
            "width": 550,
            "height": null,
            "type": "rich",
            "cache_age": "3153600000",
            "provider_name": "Twitter",
            "provider_url": "https://twitter.com",
            "version": "1.0"
        }
    ],
    "lost": [
        "https://twitter.com/ditzkoff/status/724947143031672832",
        "https://twitter.com/soniasaraiya/status/724947177898934272",
        "https://twitter.com/krunchiebutts/status/725201230109245440",
        "https://twitter.com/darrinfb/status/725207551206285312"
    ],
    "missing": []
}