{
    "meta": {
        "id": "good-tveets-7-9-2012",
        "title": "Good TVeets 7/9/2012",
        "date": 1341843442
    },
    "tweets": [
        {
            "url": "https://twitter.com/thepatrickwalsh/status/222001820346757120",
            "author_name": "Patrick Walsh",
            "author_url": "https://twitter.com/thepatrickwalsh",
            "html": "<blockquote class=\"twitter-tweet\"><p lang=\"en\" dir=\"ltr\">Just realized BREAKING BAD starts NEXT Sunday. Wandering the streets in a tattered bathrobe, openly sobbing &amp; peeing everywhere.</p>&mdash; Patrick Walsh (@thepatrickwalsh) <a href=\"https://twitter.com/thepatrickwalsh/status/222001820346757120?ref_src=twsrc%5Etfw\">July 8, 2012</a></blockquote>\n<script async src=\"https://platform.twitter.com/widgets.js\" charset=\"utf-8\"></script>\n",
            "width": 550,
            "height": null,
            "type": "rich",
            "cache_age": "3153600000",
            "provider_name": "Twitter",
            "provider_url": "https://twitter.com",
            "version": "1.0"
        },
        {
            "url": "https://twitter.com/jamieeros/status/221976477288243200",
            "author_name": "Jamie Rosengard",
            "author_url": "https://twitter.com/jamieeros",
            "html": "<blockquote class=\"twitter-tweet\"><p lang=\"en\" dir=\"ltr\">I got to the airport two hours early to watch the Wimbledon final because I&#39;m a model white person.</p>&mdash; Jamie Rosengard (@jamieeros) <a href=\"https://twitter.com/jamieeros/status/221976477288243200?ref_src=twsrc%5Etfw\">July 8, 2012</a></blockquote>\n<script async src=\"https://platform.twitter.com/widgets.js\" charset=\"utf-8\"></script>\n",
            "width": 550,
            "height": null,
            "type": "rich",
            "cache_age": "3153600000",
            "provider_name": "Twitter",
            "provider_url": "https://twitter.com",
            "version": "1.0"
        },
        {
            "url": "https://twitter.com/FayebellineW/status/221967027823312896",
            "author_name": "Faye Woods",
            "author_url": "https://twitter.com/FayebellineW",
            "html": "<blockquote class=\"twitter-tweet\"><p lang=\"en\" dir=\"ltr\">It&#39;s when I&#39;m shouting at sport on the telly that I feel I am truly my father&#39;s daughter.</p>&mdash; Faye Woods (@FayebellineW) <a href=\"https://twitter.com/FayebellineW/status/221967027823312896?ref_src=twsrc%5Etfw\">July 8, 2012</a></blockquote>\n<script async src=\"https://platform.twitter.com/widgets.js\" charset=\"utf-8\"></script>\n",
            "width": 550,
            "height": null,
            "type": "rich",
            "cache_age": "3153600000",
            "provider_name": "Twitter",
            "provider_url": "https://twitter.com",
            "version": "1.0"
        },
        {
            "url": "https://twitter.com/danowen79/status/221968408277827584",
            "author_name": "Dan Owen",
            "author_url": "https://twitter.com/danowen79",
            "html": "<blockquote class=\"twitter-tweet\"><p lang=\"en\" dir=\"ltr\">Federer will have to challenge every single call, because all of the line judges are British. <a href=\"https://twitter.com/hashtag/Wimbledon?src=hash&amp;ref_src=twsrc%5Etfw\">#Wimbledon</a></p>&mdash; Dan Owen (@danowen79) <a href=\"https://twitter.com/danowen79/status/221968408277827584?ref_src=twsrc%5Etfw\">July 8, 2012</a></blockquote>\n<script async src=\"https://platform.twitter.com/widgets.js\" charset=\"utf-8\"></script>\n",
            "width": 550,
            "height": null,
            "type": "rich",
            "cache_age": "3153600000",
            "provider_name": "Twitter",
            "provider_url": "https://twitter.com",
            "version": "1.0"
        },
        {
            "url": "https://twitter.com/danowen79/status/221969738031562752",
            "author_name": "Dan Owen",
            "author_url": "https://twitter.com/danowen79",
            "html": "<blockquote class=\"twitter-tweet\"><p lang=\"en\" dir=\"ltr\">To help, some of the ball boys have urinated on the towels they pass to Federer. <a href=\"https://twitter.com/hashtag/Wimbledon?src=hash&amp;ref_src=twsrc%5Etfw\">#Wimbledon</a></p>&mdash; Dan Owen (@danowen79) <a href=\"https://twitter.com/danowen79/status/221969738031562752?ref_src=twsrc%5Etfw\">July 8, 2012</a></blockquote>\n<script async src=\"https://platform.twitter.com/widgets.js\" charset=\"utf-8\"></script>\n",
            "width": 550,
            "height": null,
            "type": "rich",
            "cache_age": "3153600000",
            "provider_name": "Twitter",
            "provider_url": "https://twitter.com",
            "version": "1.0"
        },
        {
            "url": "https://twitter.com/cockbongo/status/221969797821382656",
            "author_name": "Tony",
            "author_url": "https://twitter.com/cockbongo",
            "html": "<blockquote class=\"twitter-tweet\"><p lang=\"en\" dir=\"ltr\">Huge amount of pressure that guy must be under this afternoon. All that expectation. Still, pretty confident Columbo will solve the case.</p>&mdash; Tony (@cockbongo) <a href=\"https://twitter.com/cockbongo/status/221969797821382656?ref_src=twsrc%5Etfw\">July 8, 2012</a></blockquote>\n<script async src=\"https://platform.twitter.com/widgets.js\" charset=\"utf-8\"></script>\n",
            "width": 550,
            "height": null,
            "type": "rich",
            "cache_age": "3153600000",
            "provider_name": "Twitter",
            "provider_url": "https://twitter.com",
            "version": "1.0"
        },
        {
            "url": "https://twitter.com/johnwarrender/status/221969972379922432",
            "author_name": "Marvel's Infinity Waco",
            "author_url": "https://twitter.com/johnwarrender",
            "html": "<blockquote class=\"twitter-tweet\"><p lang=\"en\" dir=\"ltr\">Roger Federer is today being played by one of the Prometheus Engineers wearing some foundation and a wig. <a href=\"https://twitter.com/hashtag/Wimbledon?src=hash&amp;ref_src=twsrc%5Etfw\">#Wimbledon</a></p>&mdash; Marvel&#39;s Infinity Waco (@johnwarrender) <a href=\"https://twitter.com/johnwarrender/status/221969972379922432?ref_src=twsrc%5Etfw\">July 8, 2012</a></blockquote>\n<script async src=\"https://platform.twitter.com/widgets.js\" charset=\"utf-8\"></script>\n",
            "width": 550,
            "height": null,
            "type": "rich",
            "cache_age": "3153600000",
            "provider_name": "Twitter",
            "provider_url": "https://twitter.com",
            "version": "1.0"
        },
        {
            "url": "https://twitter.com/cassiebelek/status/221970175816241152",
            "author_name": "Cassie Belek",
            "author_url": "https://twitter.com/cassiebelek",
            "html": "<blockquote class=\"twitter-tweet\"><p lang=\"en\" dir=\"ltr\">Whatever, Andy Murray. Paul Bettany already did this in 2004. <a href=\"https://twitter.com/hashtag/Wimbledon?src=hash&amp;ref_src=twsrc%5Etfw\">#Wimbledon</a></p>&mdash; Cassie Belek (@cassiebelek) <a href=\"https://twitter.com/cassiebelek/status/221970175816241152?ref_src=twsrc%5Etfw\">July 8, 2012</a></blockquote>\n<script async src=\"https://platform.twitter.com/widgets.js\" charset=\"utf-8\"></script>\n",
            "width": 550,
            "height": null,
            "type": "rich",
            "cache_age": "3153600000",
            "provider_name": "Twitter",
            "provider_url": "https://twitter.com",
            "version": "1.0"
        },
        {
            "url": "https://twitter.com/johnwarrender/status/221975399301779456",
            "author_name": "Marvel's Infinity Waco",
            "author_url": "https://twitter.com/johnwarrender",
            "html": "<blockquote class=\"twitter-tweet\"><p lang=\"en\" dir=\"ltr\">Every time Murray makes a mistake it&#39;s because he had an idea for a funny tweet mid-swing &amp; got distracted. <a href=\"https://twitter.com/hashtag/wimbledon?src=hash&amp;ref_src=twsrc%5Etfw\">#wimbledon</a></p>&mdash; Marvel&#39;s Infinity Waco (@johnwarrender) <a href=\"https://twitter.com/johnwarrender/status/221975399301779456?ref_src=twsrc%5Etfw\">July 8, 2012</a></blockquote>\n<script async src=\"https://platform.twitter.com/widgets.js\" charset=\"utf-8\"></script>\n",
            "width": 550,
            "height": null,
            "type": "rich",
            "cache_age": "3153600000",
            "provider_name": "Twitter",
            "provider_url": "https://twitter.com",
            "version": "1.0"
        },
        {
            "url": "https://twitter.com/paulwhitelaw/status/221977318845980673",
            "author_name": "Paul Whitelaw",
            "author_url": "https://twitter.com/paulwhitelaw",
            "html": "<blockquote class=\"twitter-tweet\"><p lang=\"en\" dir=\"ltr\">No-one would notice any difference if Boris Becker was replaced in the commentary box by a sandwich. <a href=\"https://twitter.com/hashtag/Wimbledon?src=hash&amp;ref_src=twsrc%5Etfw\">#Wimbledon</a></p>&mdash; Paul Whitelaw (@paulwhitelaw) <a href=\"https://twitter.com/paulwhitelaw/status/221977318845980673?ref_src=twsrc%5Etfw\">July 8, 2012</a></blockquote>\n<script async src=\"https://platform.twitter.com/widgets.js\" charset=\"utf-8\"></script>\n",
            "width": 550,
            "height": null,
            "type": "rich",
            "cache_age": "3153600000",
            "provider_name": "Twitter",
            "provider_url": "https://twitter.com",
            "version": "1.0"
        },
        {
            "url": "https://twitter.com/Queen_UK/status/222015881054666754",
            "author_name": "Elizabeth Windsor",
            "author_url": "https://twitter.com/Queen_UK",
            "html": "<blockquote class=\"twitter-tweet\"><p lang=\"en\" dir=\"ltr\">Shit bollocks sod it. <a href=\"https://twitter.com/hashtag/wimbledon?src=hash&amp;ref_src=twsrc%5Etfw\">#wimbledon</a></p>&mdash; Elizabeth Windsor (@Queen_UK) <a href=\"https://twitter.com/Queen_UK/status/222015881054666754?ref_src=twsrc%5Etfw\">July 8, 2012</a></blockquote>\n<script async src=\"https://platform.twitter.com/widgets.js\" charset=\"utf-8\"></script>\n",
            "width": 550,
            "height": null,
            "type": "rich",
            "cache_age": "3153600000",
            "provider_name": "Twitter",
            "provider_url": "https://twitter.com",
            "version": "1.0"
        },
        {
            "url": "https://twitter.com/e_morrison/status/222018380952113152",
            "author_name": "Eleanor Morrison",
            "author_url": "https://twitter.com/e_morrison",
            "html": "<blockquote class=\"twitter-tweet\"><p lang=\"en\" dir=\"ltr\">Andy&#39;s making me cry! <a href=\"https://twitter.com/hashtag/Wimbledon?src=hash&amp;ref_src=twsrc%5Etfw\">#Wimbledon</a></p>&mdash; Eleanor Morrison (@e_morrison) <a href=\"https://twitter.com/e_morrison/status/222018380952113152?ref_src=twsrc%5Etfw\">July 8, 2012</a></blockquote>\n<script async src=\"https://platform.twitter.com/widgets.js\" charset=\"utf-8\"></script>\n",
            "width": 550,
            "height": null,
            "type": "rich",
            "cache_age": "3153600000",
            "provider_name": "Twitter",
            "provider_url": "https://twitter.com",
            "version": "1.0"
        },
        {
            "url": "https://twitter.com/cassiebelek/status/222018286978736128",
            "author_name": "Cassie Belek",
            "author_url": "https://twitter.com/cassiebelek",
            "html": "<blockquote class=\"twitter-tweet\"><p lang=\"en\" dir=\"ltr\">Stop making me cry, Andy Murray! <a href=\"https://twitter.com/hashtag/Wimbledon?src=hash&amp;ref_src=twsrc%5Etfw\">#Wimbledon</a></p>&mdash; Cassie Belek (@cassiebelek) <a href=\"https://twitter.com/cassiebelek/status/222018286978736128?ref_src=twsrc%5Etfw\">July 8, 2012</a></blockquote>\n<script async src=\"https://platform.twitter.com/widgets.js\" charset=\"utf-8\"></script>\n",
            "width": 550,
            "height": null,
            "type": "rich",
            "cache_age": "3153600000",
            "provider_name": "Twitter",
            "provider_url": "https://twitter.com",
            "version": "1.0"
        },
        {
            "url": "https://twitter.com/carriesparkle/status/222018382193635330",
            "author_name": "Carrie Dunn",
            "author_url": "https://twitter.com/carriesparkle",
            "html": "<blockquote class=\"twitter-tweet\"><p lang=\"en\" dir=\"ltr\">Oh, Andy. **cries**</p>&mdash; Carrie Dunn (@carriesparkle) <a href=\"https://twitter.com/carriesparkle/status/222018382193635330?ref_src=twsrc%5Etfw\">July 8, 2012</a></blockquote>\n<script async src=\"https://platform.twitter.com/widgets.js\" charset=\"utf-8\"></script>\n",
            "width": 550,
            "height": null,
            "type": "rich",
            "cache_age": "3153600000",
            "provider_name": "Twitter",
            "provider_url": "https://twitter.com",
            "version": "1.0"
        },
        {
            "url": "https://twitter.com/savasavasava/status/222018580517109760",
            "author_name": "dr. savasavasava",
            "author_url": "https://twitter.com/savasavasava",
            "html": "<blockquote class=\"twitter-tweet\"><p lang=\"en\" dir=\"ltr\">::crying:: with Andy.</p>&mdash; dr. savasavasava (@savasavasava) <a href=\"https://twitter.com/savasavasava/status/222018580517109760?ref_src=twsrc%5Etfw\">July 8, 2012</a></blockquote>\n<script async src=\"https://platform.twitter.com/widgets.js\" charset=\"utf-8\"></script>\n",
            "width": 550,
            "height": null,
            "type": "rich",
            "cache_age": "3153600000",
            "provider_name": "Twitter",
            "provider_url": "https://twitter.com",
            "version": "1.0"
        },
        {
            "url": "https://twitter.com/GillianJacobs/status/222019077558910977",
            "author_name": "Gillian Jacobs",
            "author_url": "https://twitter.com/GillianJacobs",
            "html": "<blockquote class=\"twitter-tweet\"><p lang=\"en\" dir=\"ltr\">.<a href=\"https://twitter.com/andy_murray?ref_src=twsrc%5Etfw\">@andy_murray</a> made me cry</p>&mdash; Gillian Jacobs (@GillianJacobs) <a href=\"https://twitter.com/GillianJacobs/status/222019077558910977?ref_src=twsrc%5Etfw\">July 8, 2012</a></blockquote>\n<script async src=\"https://platform.twitter.com/widgets.js\" charset=\"utf-8\"></script>\n",
            "width": 550,
            "height": null,
            "type": "rich",
            "cache_age": "3153600000",
            "provider_name": "Twitter",
            "provider_url": "https://twitter.com",
            "version": "1.0"
        },
        {
            "url": "https://twitter.com/Memles/status/222019487032029186",
            "author_name": "Myles McNutt",
            "author_url": "https://twitter.com/Memles",
            "html": "<blockquote class=\"twitter-tweet\"><p lang=\"en\" dir=\"ltr\">Oh Andy / You came and you lost without flailing / And you made us verklempt / Oh Andy. <a href=\"https://twitter.com/hashtag/Wimbledon?src=hash&amp;ref_src=twsrc%5Etfw\">#Wimbledon</a></p>&mdash; Myles McNutt (@Memles) <a href=\"https://twitter.com/Memles/status/222019487032029186?ref_src=twsrc%5Etfw\">July 8, 2012</a></blockquote>\n<script async src=\"https://platform.twitter.com/widgets.js\" charset=\"utf-8\"></script>\n",
            "width": 550,
            "height": null,
            "type": "rich",
            "cache_age": "3153600000",
            "provider_name": "Twitter",
            "provider_url": "https://twitter.com",
            "version": "1.0"
        },
        {
            "url": "https://twitter.com/danowen79/status/222019842306347009",
            "author_name": "Dan Owen",
            "author_url": "https://twitter.com/danowen79",
            "html": "<blockquote class=\"twitter-tweet\"><p lang=\"en\" dir=\"ltr\">Little-known <a href=\"https://twitter.com/hashtag/Wimbledon?src=hash&amp;ref_src=twsrc%5Etfw\">#Wimbledon</a> fact: the loser has to cut the grass next year.</p>&mdash; Dan Owen (@danowen79) <a href=\"https://twitter.com/danowen79/status/222019842306347009?ref_src=twsrc%5Etfw\">July 8, 2012</a></blockquote>\n<script async src=\"https://platform.twitter.com/widgets.js\" charset=\"utf-8\"></script>\n",
            "width": 550,
            "height": null,
            "type": "rich",
            "cache_age": "3153600000",
            "provider_name": "Twitter",
            "provider_url": "https://twitter.com",
            "version": "1.0"
        },
        {
            "url": "https://twitter.com/paulwhitelaw/status/222033335348768769",
            "author_name": "Paul Whitelaw",
            "author_url": "https://twitter.com/paulwhitelaw",
            "html": "<blockquote class=\"twitter-tweet\"><p lang=\"en\" dir=\"ltr\">Mixed doubles would be much more interesting if at least one of the players was some sort of shark-arachnid hybrid. <a href=\"https://twitter.com/hashtag/Wimbledon?src=hash&amp;ref_src=twsrc%5Etfw\">#Wimbledon</a></p>&mdash; Paul Whitelaw (@paulwhitelaw) <a href=\"https://twitter.com/paulwhitelaw/status/222033335348768769?ref_src=twsrc%5Etfw\">July 8, 2012</a></blockquote>\n<script async src=\"https://platform.twitter.com/widgets.js\" charset=\"utf-8\"></script>\n",
            "width": 550,
            "height": null,
            "type": "rich",
            "cache_age": "3153600000",
            "provider_name": "Twitter",
            "provider_url": "https://twitter.com",
            "version": "1.0"
        },
        {
            "url": "https://twitter.com/CameronYardeJnr/status/222036302260994048",
            "author_name": "Cameron Yarde Jnr",
            "author_url": "https://twitter.com/CameronYardeJnr",
            "html": "<blockquote class=\"twitter-tweet\"><p lang=\"en\" dir=\"ltr\">Roger Federer is an incredible tennis player. But does anybody else see  Quentin Tarantino holding a tennis racquet? Just me then.</p>&mdash; Cameron Yarde Jnr (@CameronYardeJnr) <a href=\"https://twitter.com/CameronYardeJnr/status/222036302260994048?ref_src=twsrc%5Etfw\">July 8, 2012</a></blockquote>\n<script async src=\"https://platform.twitter.com/widgets.js\" charset=\"utf-8\"></script>\n",
            "width": 550,
            "height": null,
            "type": "rich",
            "cache_age": "3153600000",
            "provider_name": "Twitter",
            "provider_url": "https://twitter.com",
            "version": "1.0"
        },
        {
            "url": "https://twitter.com/shawnries/status/222027170787229697",
            "author_name": "Shawn Ries",
            "author_url": "https://twitter.com/shawnries",
            "html": "<blockquote class=\"twitter-tweet\"><p lang=\"en\" dir=\"ltr\">Netflix has an amazing business model. People basically pay them to say, &quot;Uch, there&#39;s nothing good on Netflix.&quot;</p>&mdash; Shawn Ries (@shawnries) <a href=\"https://twitter.com/shawnries/status/222027170787229697?ref_src=twsrc%5Etfw\">July 8, 2012</a></blockquote>\n<script async src=\"https://platform.twitter.com/widgets.js\" charset=\"utf-8\"></script>\n",
            "width": 550,
            "height": null,
            "type": "rich",
            "cache_age": "3153600000",
            "provider_name": "Twitter",
            "provider_url": "https://twitter.com",
            "version": "1.0"
        },
        {
            "url": "https://twitter.com/AgentTrainee/status/222049553753456640",
            "author_name": "Agent Trainee",
            "author_url": "https://twitter.com/AgentTrainee",
            "html": "<blockquote class=\"twitter-tweet\"><p lang=\"en\" dir=\"ltr\">And why do we eat at Toast? WHY? Well, because The Hills filmed here and so did Entourage and US Weekly writes about it. I think that&#39;s why.</p>&mdash; Agent Trainee (@AgentTrainee) <a href=\"https://twitter.com/AgentTrainee/status/222049553753456640?ref_src=twsrc%5Etfw\">July 8, 2012</a></blockquote>\n<script async src=\"https://platform.twitter.com/widgets.js\" charset=\"utf-8\"></script>\n",
            "width": 550,
            "height": null,
            "type": "rich",
            "cache_age": "3153600000",
            "provider_name": "Twitter",
            "provider_url": "https://twitter.com",
            "version": "1.0"
        },
        {
            "url": "https://twitter.com/MarkHarrisNYC/status/222060505949417472",
            "author_name": "Mark Harris",
            "author_url": "https://twitter.com/MarkHarrisNYC",
            "html": "<blockquote class=\"twitter-tweet\"><p lang=\"en\" dir=\"ltr\">Probably enough time has passed by now for a Battleship reboot.</p>&mdash; Mark Harris (@MarkHarrisNYC) <a href=\"https://twitter.com/MarkHarrisNYC/status/222060505949417472?ref_src=twsrc%5Etfw\">July 8, 2012</a></blockquote>\n<script async src=\"https://platform.twitter.com/widgets.js\" charset=\"utf-8\"></script>\n",
            "width": 550,
            "height": null,
            "type": "rich",
            "cache_age": "3153600000",
            "provider_name": "Twitter",
            "provider_url": "https://twitter.com",
            "version": "1.0"
        },
        {
            "url": "https://twitter.com/mousterpiece/status/222060698589601792",
            "author_name": "Josh Spiegel",
            "author_url": "https://twitter.com/mousterpiece",
            "html": "<blockquote class=\"twitter-tweet\"><p lang=\"en\" dir=\"ltr\">Just recast Taylor Kitsch with Channing Tatum. RT <a href=\"https://twitter.com/MarkHarrisNYC?ref_src=twsrc%5Etfw\">@MarkHarrisNYC</a>: Probably enough time has passed by now for a Battleship reboot.</p>&mdash; Josh Spiegel (@mousterpiece) <a href=\"https://twitter.com/mousterpiece/status/222060698589601792?ref_src=twsrc%5Etfw\">July 8, 2012</a></blockquote>\n<script async src=\"https://platform.twitter.com/widgets.js\" charset=\"utf-8\"></script>\n",
            "width": 550,
            "height": null,
            "type": "rich",
            "cache_age": "3153600000",
            "provider_name": "Twitter",
            "provider_url": "https://twitter.com",
            "version": "1.0"
        },
        {
            "url": "https://twitter.com/thesideofmyface/status/222067534835363840",
            "author_name": "FLAMES ON",
            "author_url": "https://twitter.com/thesideofmyface",
            "html": "<blockquote class=\"twitter-tweet\"><p lang=\"en\" dir=\"ltr\">It occurred to me today at my Second City class that if I use every bathrom stall at some point, Tina Fey and I will have shared a toilet.</p>&mdash; FLAMES ON (@thesideofmyface) <a href=\"https://twitter.com/thesideofmyface/status/222067534835363840?ref_src=twsrc%5Etfw\">July 8, 2012</a></blockquote>\n<script async src=\"https://platform.twitter.com/widgets.js\" charset=\"utf-8\"></script>\n",
            "width": 550,
            "height": null,
            "type": "rich",
            "cache_age": "3153600000",
            "provider_name": "Twitter",
            "provider_url": "https://twitter.com",
            "version": "1.0"
        },
        {
            "url": "https://twitter.com/RichieOnTV/status/222069123335716865",
            "author_name": "Richie",
            "author_url": "https://twitter.com/RichieOnTV",
            "html": "<blockquote class=\"twitter-tweet\"><p lang=\"en\" dir=\"ltr\">Now homophobes and every actor on The CW will have something in common: Bing as their default search engine. <a href=\"http://t.co/IPRUTFHg\">http://t.co/IPRUTFHg</a></p>&mdash; Richie (@RichieOnTV) <a href=\"https://twitter.com/RichieOnTV/status/222069123335716865?ref_src=twsrc%5Etfw\">July 8, 2012</a></blockquote>\n<script async src=\"https://platform.twitter.com/widgets.js\" charset=\"utf-8\"></script>\n",
            "width": 550,
            "height": null,
            "type": "rich",
            "cache_age": "3153600000",
            "provider_name": "Twitter",
            "provider_url": "https://twitter.com",
            "version": "1.0"
        },
        {
            "url": "https://twitter.com/jlschaefer/status/222080036889571329",
            "author_name": "Jennifer Schaefer",
            "author_url": "https://twitter.com/jlschaefer",
            "html": "<blockquote class=\"twitter-tweet\"><p lang=\"en\" dir=\"ltr\">Don Draper playing softball will be best thing to happen to Monday <a href=\"https://twitter.com/GoodTVeets?ref_src=twsrc%5Etfw\">@GoodTVeets</a> since Smash. MT <a href=\"https://twitter.com/MLB?ref_src=twsrc%5Etfw\">@MLB</a>: Jon Hamm’s jersey <a href=\"http://t.co/ltqdtTYL\">pic.twitter.com/ltqdtTYL</a></p>&mdash; Jennifer Schaefer (@jlschaefer) <a href=\"https://twitter.com/jlschaefer/status/222080036889571329?ref_src=twsrc%5Etfw\">July 8, 2012</a></blockquote>\n<script async src=\"https://platform.twitter.com/widgets.js\" charset=\"utf-8\"></script>\n",
            "width": 550,
            "height": null,
            "type": "rich",
            "cache_age": "3153600000",
            "provider_name": "Twitter",
            "provider_url": "https://twitter.com",
            "version": "1.0"
        },
        {
            "url": "https://twitter.com/arrabin56/status/222080962203361280",
            "author_name": "(((Andrew Rabin)))📎",
            "author_url": "https://twitter.com/arrabin56",
            "html": "<blockquote class=\"twitter-tweet\"><p lang=\"en\" dir=\"ltr\">Spoiler- my tweets will be about <a href=\"https://twitter.com/chrissyteigen?ref_src=twsrc%5Etfw\">@chrissyteigen</a> MT <a href=\"https://twitter.com/jlschaefer?ref_src=twsrc%5Etfw\">@jlschaefer</a>: [Hamm] playing softball will be best thing for Mon. <a href=\"https://twitter.com/GoodTVeets?ref_src=twsrc%5Etfw\">@GoodTVeets</a> since Smash.</p>&mdash; (((Andrew Rabin)))📎 (@arrabin56) <a href=\"https://twitter.com/arrabin56/status/222080962203361280?ref_src=twsrc%5Etfw\">July 8, 2012</a></blockquote>\n<script async src=\"https://platform.twitter.com/widgets.js\" charset=\"utf-8\"></script>\n",
            "width": 550,
            "height": null,
            "type": "rich",
            "cache_age": "3153600000",
            "provider_name": "Twitter",
            "provider_url": "https://twitter.com",
            "version": "1.0"
        },
        {
            "url": "https://twitter.com/MLB/status/222084078936137729",
            "author_name": "MLB",
            "author_url": "https://twitter.com/MLB",
            "html": "<blockquote class=\"twitter-tweet\"><p lang=\"en\" dir=\"ltr\">Missouri boys Jon Hamm and <a href=\"https://twitter.com/ericstonestreet?ref_src=twsrc%5Etfw\">@ericstonestreet</a> have their game faces on for the <a href=\"https://twitter.com/hashtag/CelebrityGame?src=hash&amp;ref_src=twsrc%5Etfw\">#CelebrityGame</a>: <a href=\"http://t.co/lC4K417k\">pic.twitter.com/lC4K417k</a></p>&mdash; MLB (@MLB) <a href=\"https://twitter.com/MLB/status/222084078936137729?ref_src=twsrc%5Etfw\">July 8, 2012</a></blockquote>\n<script async src=\"https://platform.twitter.com/widgets.js\" charset=\"utf-8\"></script>\n",
            "width": 550,
            "height": null,
            "type": "rich",
            "cache_age": "3153600000",
            "provider_name": "Twitter",
            "provider_url": "https://twitter.com",
            "version": "1.0"
        },
        {
            "url": "https://twitter.com/LouisPeitzman/status/222084395010498560",
            "author_name": "Louis Peitzman",
            "author_url": "https://twitter.com/LouisPeitzman",
            "html": "<blockquote class=\"twitter-tweet\"><p lang=\"en\" dir=\"ltr\">&quot;By clicking &#39;Tweet,&#39; you consent to having your tweet repurposed in a useless article titled &#39;Twitter Reacts to Ernest Borgnine&#39;s Death.&#39;&quot;</p>&mdash; Louis Peitzman (@LouisPeitzman) <a href=\"https://twitter.com/LouisPeitzman/status/222084395010498560?ref_src=twsrc%5Etfw\">July 8, 2012</a></blockquote>\n<script async src=\"https://platform.twitter.com/widgets.js\" charset=\"utf-8\"></script>\n",
            "width": 550,
            "height": null,
            "type": "rich",
            "cache_age": "3153600000",
            "provider_name": "Twitter",
            "provider_url": "https://twitter.com",
            "version": "1.0"
        },
        {
            "url": "https://twitter.com/robertdsheridan/status/222091858455691266",
            "author_name": "Rob Sheridan",
            "author_url": "https://twitter.com/robertdsheridan",
            "html": "<blockquote class=\"twitter-tweet\"><p lang=\"en\" dir=\"ltr\">McHale and Sheriff Taylor lost in the same week. Hug your television. :(</p>&mdash; Rob Sheridan (@robertdsheridan) <a href=\"https://twitter.com/robertdsheridan/status/222091858455691266?ref_src=twsrc%5Etfw\">July 8, 2012</a></blockquote>\n<script async src=\"https://platform.twitter.com/widgets.js\" charset=\"utf-8\"></script>\n",
            "width": 550,
            "height": null,
            "type": "rich",
            "cache_age": "3153600000",
            "provider_name": "Twitter",
            "provider_url": "https://twitter.com",
            "version": "1.0"
        },
        {
            "url": "https://twitter.com/AndrewDaar/status/222108077753774080",
            "author_name": "Poe Daar-meron",
            "author_url": "https://twitter.com/AndrewDaar",
            "html": "<blockquote class=\"twitter-tweet\"><p lang=\"en\" dir=\"ltr\">Dear HBO: Please create a show called LADIES, featuring Asha Greyjoy, Brienne of Tarth, Arya Stark, and Arienne Martell living in Brooklyn.</p>&mdash; Poe Daar-meron (@AndrewDaar) <a href=\"https://twitter.com/AndrewDaar/status/222108077753774080?ref_src=twsrc%5Etfw\">July 8, 2012</a></blockquote>\n<script async src=\"https://platform.twitter.com/widgets.js\" charset=\"utf-8\"></script>\n",
            "width": 550,
            "height": null,
            "type": "rich",
            "cache_age": "3153600000",
            "provider_name": "Twitter",
            "provider_url": "https://twitter.com",
            "version": "1.0"
        },
        {
            "url": "https://twitter.com/zhandlen/status/222120464733052929",
            "author_name": "Bah, Handlen!",
            "author_url": "https://twitter.com/zhandlen",
            "html": "<blockquote class=\"twitter-tweet\"><p lang=\"en\" dir=\"ltr\">Well, I _was_ just going to watch one episode of Slings &amp; Arrows, but it turns out it&#39;s basically impossible to do that.</p>&mdash; Bah, Handlen! (@zhandlen) <a href=\"https://twitter.com/zhandlen/status/222120464733052929?ref_src=twsrc%5Etfw\">July 9, 2012</a></blockquote>\n<script async src=\"https://platform.twitter.com/widgets.js\" charset=\"utf-8\"></script>\n",
            "width": 550,
            "height": null,
            "type": "rich",
            "cache_age": "3153600000",
            "provider_name": "Twitter",
            "provider_url": "https://twitter.com",
            "version": "1.0"
        },
        {
            "url": "https://twitter.com/JennyJohnsonHi5/status/222143693673611265",
            "author_name": "Jenny Johnson",
            "author_url": "https://twitter.com/JennyJohnsonHi5",
            "html": "<blockquote class=\"twitter-tweet\"><p lang=\"en\" dir=\"ltr\">The secret ingredient in Gordon Ramsay&#39;s cooking is hate.</p>&mdash; Jenny Johnson (@JennyJohnsonHi5) <a href=\"https://twitter.com/JennyJohnsonHi5/status/222143693673611265?ref_src=twsrc%5Etfw\">July 9, 2012</a></blockquote>\n<script async src=\"https://platform.twitter.com/widgets.js\" charset=\"utf-8\"></script>\n",
            "width": 550,
            "height": null,
            "type": "rich",
            "cache_age": "3153600000",
            "provider_name": "Twitter",
            "provider_url": "https://twitter.com",
            "version": "1.0"
        },
        {
            "url": "https://twitter.com/kenlowery/status/222149169807228929",
            "author_name": "Ken! The Herald Angels Sing",
            "author_url": "https://twitter.com/kenlowery",
            "html": "<blockquote class=\"twitter-tweet\"><p lang=\"en\" dir=\"ltr\">Is there anything better than Judy Greer screaming &quot;you&#39;re not my supervisor&quot;? I am not sure there is.</p>&mdash; Ken! The Herald Angels Sing (@kenlowery) <a href=\"https://twitter.com/kenlowery/status/222149169807228929?ref_src=twsrc%5Etfw\">July 9, 2012</a></blockquote>\n<script async src=\"https://platform.twitter.com/widgets.js\" charset=\"utf-8\"></script>\n",
            "width": 550,
            "height": null,
            "type": "rich",
            "cache_age": "3153600000",
            "provider_name": "Twitter",
            "provider_url": "https://twitter.com",
            "version": "1.0"
        },
        {
            "url": "https://twitter.com/VDOOZER/status/222155995453988865",
            "author_name": "Bill Lawrence",
            "author_url": "https://twitter.com/VDOOZER",
            "html": "<blockquote class=\"twitter-tweet\"><p lang=\"en\" dir=\"ltr\">Psyched for Dateline/48hrs/48hrsmystery tonight. It&#39;s that one where it turns out that the husband murdered his wife.</p>&mdash; Bill Lawrence (@VDOOZER) <a href=\"https://twitter.com/VDOOZER/status/222155995453988865?ref_src=twsrc%5Etfw\">July 9, 2012</a></blockquote>\n<script async src=\"https://platform.twitter.com/widgets.js\" charset=\"utf-8\"></script>\n",
            "width": 550,
            "height": null,
            "type": "rich",
            "cache_age": "3153600000",
            "provider_name": "Twitter",
            "provider_url": "https://twitter.com",
            "version": "1.0"
        },
        {
            "url": "https://twitter.com/lnpalmer2000/status/222157894962003971",
            "author_name": "Lindsay Palmer",
            "author_url": "https://twitter.com/lnpalmer2000",
            "html": "<blockquote class=\"twitter-tweet\"><p lang=\"en\" dir=\"ltr\">Now that I&#39;m obsessed w/HGTV, I often say things like, &quot;This house has good bones.&quot;</p>&mdash; Lindsay Palmer (@lnpalmer2000) <a href=\"https://twitter.com/lnpalmer2000/status/222157894962003971?ref_src=twsrc%5Etfw\">July 9, 2012</a></blockquote>\n<script async src=\"https://platform.twitter.com/widgets.js\" charset=\"utf-8\"></script>\n",
            "width": 550,
            "height": null,
            "type": "rich",
            "cache_age": "3153600000",
            "provider_name": "Twitter",
            "provider_url": "https://twitter.com",
            "version": "1.0"
        },
        {
            "url": "https://twitter.com/cassiebelek/status/222171978113626113",
            "author_name": "Cassie Belek",
            "author_url": "https://twitter.com/cassiebelek",
            "html": "<blockquote class=\"twitter-tweet\"><p lang=\"en\" dir=\"ltr\">This weekend I watched eight hours of &quot;Extreme Makeover: Weight Loss Edition.&quot; I am the only person on Twitter who can say this.</p>&mdash; Cassie Belek (@cassiebelek) <a href=\"https://twitter.com/cassiebelek/status/222171978113626113?ref_src=twsrc%5Etfw\">July 9, 2012</a></blockquote>\n<script async src=\"https://platform.twitter.com/widgets.js\" charset=\"utf-8\"></script>\n",
            "width": 550,
            "height": null,
            "type": "rich",
            "cache_age": "3153600000",
            "provider_name": "Twitter",
            "provider_url": "https://twitter.com",
            "version": "1.0"
        },
        {
            "url": "https://twitter.com/danCLYNE/status/222185298140991488",
            "author_name": "Dan Clyne",
            "author_url": "https://twitter.com/danCLYNE",
            "html": "<blockquote class=\"twitter-tweet\"><p lang=\"en\" dir=\"ltr\">&quot;Waterworld 2 is dead if Tripplehorn can&#39;t do it&quot; Kevin Costner loudly said to no one at his back table at Veggie Grill.</p>&mdash; Dan Clyne (@danCLYNE) <a href=\"https://twitter.com/danCLYNE/status/222185298140991488?ref_src=twsrc%5Etfw\">July 9, 2012</a></blockquote>\n<script async src=\"https://platform.twitter.com/widgets.js\" charset=\"utf-8\"></script>\n",
            "width": 550,
            "height": null,
            "type": "rich",
            "cache_age": "3153600000",
            "provider_name": "Twitter",
            "provider_url": "https://twitter.com",
            "version": "1.0"
        },
        {
            "url": "https://twitter.com/tmvogel/status/222138359143866368",
            "author_name": "Teri Vogel",
            "author_url": "https://twitter.com/tmvogel",
            "html": "<blockquote class=\"twitter-tweet\"><p lang=\"en\" dir=\"ltr\">I&#39;m OK with <a href=\"https://twitter.com/hashtag/TrueBlood?src=hash&amp;ref_src=twsrc%5Etfw\">#TrueBlood</a> being WTF crazy. But it&#39;s the boring that&#39;s driving me nuts.</p>&mdash; Teri Vogel (@tmvogel) <a href=\"https://twitter.com/tmvogel/status/222138359143866368?ref_src=twsrc%5Etfw\">July 9, 2012</a></blockquote>\n<script async src=\"https://platform.twitter.com/widgets.js\" charset=\"utf-8\"></script>\n",
            "width": 550,
            "height": null,
            "type": "rich",
            "cache_age": "3153600000",
            "provider_name": "Twitter",
            "provider_url": "https://twitter.com",
            "version": "1.0"
        },
        {
            "url": "https://twitter.com/frazbelina/status/222250329390067713",
            "author_name": "Emma Fraser",
            "author_url": "https://twitter.com/frazbelina",
            "html": "<blockquote class=\"twitter-tweet\"><p lang=\"en\" dir=\"ltr\">Somehow this season of True Blood has made Tara likeable and Sookie a badass. It&#39;s not a perfect show but this is pretty awesome.</p>&mdash; Emma Fraser (@frazbelina) <a href=\"https://twitter.com/frazbelina/status/222250329390067713?ref_src=twsrc%5Etfw\">July 9, 2012</a></blockquote>\n<script async src=\"https://platform.twitter.com/widgets.js\" charset=\"utf-8\"></script>\n",
            "width": 550,
            "height": null,
            "type": "rich",
            "cache_age": "3153600000",
            "provider_name": "Twitter",
            "provider_url": "https://twitter.com",
            "version": "1.0"
        },
        {
            "url": "https://twitter.com/danielletbd/status/222184246897418241",
            "author_name": "Danielle Turchiano",
            "author_url": "https://twitter.com/danielletbd",
            "html": "<blockquote class=\"twitter-tweet\"><p lang=\"en\" dir=\"ltr\">Yelling is not acting. Can you guess what I&#39;m watching?</p>&mdash; Danielle Turchiano (@danielletbd) <a href=\"https://twitter.com/danielletbd/status/222184246897418241?ref_src=twsrc%5Etfw\">July 9, 2012</a></blockquote>\n<script async src=\"https://platform.twitter.com/widgets.js\" charset=\"utf-8\"></script>\n",
            "width": 550,
            "height": null,
            "type": "rich",
            "cache_age": "3153600000",
            "provider_name": "Twitter",
            "provider_url": "https://twitter.com",
            "version": "1.0"
        },
        {
            "url": "https://twitter.com/zhandlen/status/222136780286210048",
            "author_name": "Bah, Handlen!",
            "author_url": "https://twitter.com/zhandlen",
            "html": "<blockquote class=\"twitter-tweet\"><p lang=\"en\" dir=\"ltr\">&quot;The news-&quot; &quot;Yes?&quot; &quot;The news is about who we were. I want to talk about who we _are_.&quot; &quot;So, the... nows?&quot; <a href=\"https://twitter.com/hashtag/possiblenewsroomdialogue?src=hash&amp;ref_src=twsrc%5Etfw\">#possiblenewsroomdialogue</a></p>&mdash; Bah, Handlen! (@zhandlen) <a href=\"https://twitter.com/zhandlen/status/222136780286210048?ref_src=twsrc%5Etfw\">July 9, 2012</a></blockquote>\n<script async src=\"https://platform.twitter.com/widgets.js\" charset=\"utf-8\"></script>\n",
            "width": 550,
            "height": null,
            "type": "rich",
            "cache_age": "3153600000",
            "provider_name": "Twitter",
            "provider_url": "https://twitter.com",
            "version": "1.0"
        },
        {
            "url": "https://twitter.com/ellievhall/status/222143579517235202",
            "author_name": "Ellie Hall",
            "author_url": "https://twitter.com/ellievhall",
            "html": "<blockquote class=\"twitter-tweet\"><p lang=\"en\" dir=\"ltr\">&quot;Walk with me.&quot; <a href=\"https://twitter.com/hashtag/possiblenewsroomdialogue?src=hash&amp;ref_src=twsrc%5Etfw\">#possiblenewsroomdialogue</a></p>&mdash; Ellie Hall (@ellievhall) <a href=\"https://twitter.com/ellievhall/status/222143579517235202?ref_src=twsrc%5Etfw\">July 9, 2012</a></blockquote>\n<script async src=\"https://platform.twitter.com/widgets.js\" charset=\"utf-8\"></script>\n",
            "width": 550,
            "height": null,
            "type": "rich",
            "cache_age": "3153600000",
            "provider_name": "Twitter",
            "provider_url": "https://twitter.com",
            "version": "1.0"
        },
        {
            "url": "https://twitter.com/MeredithBlake/status/222137659496206337",
            "author_name": "Meredith Blake",
            "author_url": "https://twitter.com/MeredithBlake",
            "html": "<blockquote class=\"twitter-tweet\"><p lang=\"en\" dir=\"ltr\">Can we all agree that the worst part of <a href=\"https://twitter.com/hashtag/TheNewsroom?src=hash&amp;ref_src=twsrc%5Etfw\">#TheNewsroom</a> is the nostalgic credit sequence with the inspirational string music?</p>&mdash; Meredith Blake (@MeredithBlake) <a href=\"https://twitter.com/MeredithBlake/status/222137659496206337?ref_src=twsrc%5Etfw\">July 9, 2012</a></blockquote>\n<script async src=\"https://platform.twitter.com/widgets.js\" charset=\"utf-8\"></script>\n",
            "width": 550,
            "height": null,
            "type": "rich",
            "cache_age": "3153600000",
            "provider_name": "Twitter",
            "provider_url": "https://twitter.com",
            "version": "1.0"
        },
        {
            "url": "https://twitter.com/smithsj/status/222146917818306561",
            "author_name": "Stephen Smith",
            "author_url": "https://twitter.com/smithsj",
            "html": "<blockquote class=\"twitter-tweet\"><p lang=\"en\" dir=\"ltr\">Bitching about people bitching about people bitching about The Newsroom is the new bitching about people bitching about The Newsroom.</p>&mdash; Stephen Smith (@smithsj) <a href=\"https://twitter.com/smithsj/status/222146917818306561?ref_src=twsrc%5Etfw\">July 9, 2012</a></blockquote>\n<script async src=\"https://platform.twitter.com/widgets.js\" charset=\"utf-8\"></script>\n",
            "width": 550,
            "height": null,
            "type": "rich",
            "cache_age": "3153600000",
            "provider_name": "Twitter",
            "provider_url": "https://twitter.com",
            "version": "1.0"
        },
        {
            "url": "https://twitter.com/danieltwalters/status/222152568749555712",
            "author_name": "Daniel Walters",
            "author_url": "https://twitter.com/danieltwalters",
            "html": "<blockquote class=\"twitter-tweet\"><p lang=\"en\" dir=\"ltr\">Idea for a movie: A car accident causes Aaron Sorkin to get stuck in a small town for a week, where he slowly learns to respect them.</p>&mdash; Daniel Walters (@danieltwalters) <a href=\"https://twitter.com/danieltwalters/status/222152568749555712?ref_src=twsrc%5Etfw\">July 9, 2012</a></blockquote>\n<script async src=\"https://platform.twitter.com/widgets.js\" charset=\"utf-8\"></script>\n",
            "width": 550,
            "height": null,
            "type": "rich",
            "cache_age": "3153600000",
            "provider_name": "Twitter",
            "provider_url": "https://twitter.com",
            "version": "1.0"
        },
        {
            "url": "https://twitter.com/realchriswilson/status/222155288369836032",
            "author_name": "🎄Chris Wilson🎄",
            "author_url": "https://twitter.com/realchriswilson",
            "html": "<blockquote class=\"twitter-tweet\"><p lang=\"en\" dir=\"ltr\">The best thing about &quot;The Newsroom&quot; is that &quot;Breaking Bad&quot; starts next week.</p>&mdash; 🎄Chris Wilson🎄 (@realchriswilson) <a href=\"https://twitter.com/realchriswilson/status/222155288369836032?ref_src=twsrc%5Etfw\">July 9, 2012</a></blockquote>\n<script async src=\"https://platform.twitter.com/widgets.js\" charset=\"utf-8\"></script>\n",
            "width": 550,
            "height": null,
            "type": "rich",
            "cache_age": "3153600000",
            "provider_name": "Twitter",
            "provider_url": "https://twitter.com",
            "version": "1.0"
        },
        {
            "url": "https://twitter.com/JamesWolcott/status/222156208994385921",
            "author_name": "James Wolcott",
            "author_url": "https://twitter.com/JamesWolcott",
            "html": "<blockquote class=\"twitter-tweet\"><p lang=\"en\" dir=\"ltr\">Why can&#39;t the women on this show hold their shit together? <a href=\"https://twitter.com/hashtag/TheNewsroom?src=hash&amp;ref_src=twsrc%5Etfw\">#TheNewsroom</a></p>&mdash; James Wolcott (@JamesWolcott) <a href=\"https://twitter.com/JamesWolcott/status/222156208994385921?ref_src=twsrc%5Etfw\">July 9, 2012</a></blockquote>\n<script async src=\"https://platform.twitter.com/widgets.js\" charset=\"utf-8\"></script>\n",
            "width": 550,
            "height": null,
            "type": "rich",
            "cache_age": "3153600000",
            "provider_name": "Twitter",
            "provider_url": "https://twitter.com",
            "version": "1.0"
        },
        {
            "url": "https://twitter.com/scott_tobias/status/222159651859464196",
            "author_name": "Scott Tobias",
            "author_url": "https://twitter.com/scott_tobias",
            "html": "<blockquote class=\"twitter-tweet\"><p lang=\"en\" dir=\"ltr\">How&#39;s everyone enjoying David Frum&#39;s <a href=\"https://twitter.com/hashtag/TheNewsroom?src=hash&amp;ref_src=twsrc%5Etfw\">#TheNewsroom</a> tonight?</p>&mdash; Scott Tobias (@scott_tobias) <a href=\"https://twitter.com/scott_tobias/status/222159651859464196?ref_src=twsrc%5Etfw\">July 9, 2012</a></blockquote>\n<script async src=\"https://platform.twitter.com/widgets.js\" charset=\"utf-8\"></script>\n",
            "width": 550,
            "height": null,
            "type": "rich",
            "cache_age": "3153600000",
            "provider_name": "Twitter",
            "provider_url": "https://twitter.com",
            "version": "1.0"
        },
        {
            "url": "https://twitter.com/digifreak642/status/222163228795486211",
            "author_name": "Person of Mattress",
            "author_url": "https://twitter.com/digifreak642",
            "html": "<blockquote class=\"twitter-tweet\"><p lang=\"en\" dir=\"ltr\">&quot;&quot;The Newsroom&quot; is important television, the closest we&#39;ve had to &quot;must-see TV&quot; in recent years.&quot; -- Dan Rather, TV critic</p>&mdash; Person of Mattress (@digifreak642) <a href=\"https://twitter.com/digifreak642/status/222163228795486211?ref_src=twsrc%5Etfw\">July 9, 2012</a></blockquote>\n<script async src=\"https://platform.twitter.com/widgets.js\" charset=\"utf-8\"></script>\n",
            "width": 550,
            "height": null,
            "type": "rich",
            "cache_age": "3153600000",
            "provider_name": "Twitter",
            "provider_url": "https://twitter.com",
            "version": "1.0"
        },
        {
            "url": "https://twitter.com/TVandDinners/status/222163504155734018",
            "author_name": "Carrie Raisler",
            "author_url": "https://twitter.com/TVandDinners",
            "html": "<blockquote class=\"twitter-tweet\"><p lang=\"en\" dir=\"ltr\">Lulz, Rather. Pick up your remote more often.</p>&mdash; Carrie Raisler (@TVandDinners) <a href=\"https://twitter.com/TVandDinners/status/222163504155734018?ref_src=twsrc%5Etfw\">July 9, 2012</a></blockquote>\n<script async src=\"https://platform.twitter.com/widgets.js\" charset=\"utf-8\"></script>\n",
            "width": 550,
            "height": null,
            "type": "rich",
            "cache_age": "3153600000",
            "provider_name": "Twitter",
            "provider_url": "https://twitter.com",
            "version": "1.0"
        },
        {
            "url": "https://twitter.com/mousterpiece/status/222163743533051904",
            "author_name": "Josh Spiegel",
            "author_url": "https://twitter.com/mousterpiece",
            "html": "<blockquote class=\"twitter-tweet\"><p lang=\"en\" dir=\"ltr\"><a href=\"https://twitter.com/TVandDinners?ref_src=twsrc%5Etfw\">@TVandDinners</a>: He watches HDNet exclusively. This is a big step for him, watching HBO.</p>&mdash; Josh Spiegel (@mousterpiece) <a href=\"https://twitter.com/mousterpiece/status/222163743533051904?ref_src=twsrc%5Etfw\">July 9, 2012</a></blockquote>\n<script async src=\"https://platform.twitter.com/widgets.js\" charset=\"utf-8\"></script>\n",
            "width": 550,
            "height": null,
            "type": "rich",
            "cache_age": "3153600000",
            "provider_name": "Twitter",
            "provider_url": "https://twitter.com",
            "version": "1.0"
        },
        {
            "url": "https://twitter.com/fymaxwell/status/222166869665255424",
            "author_name": "Max Dawson",
            "author_url": "https://twitter.com/fymaxwell",
            "html": "<blockquote class=\"twitter-tweet\"><p lang=\"en\" dir=\"ltr\">Newsroom isn&#39;t just tedious, it&#39;s factually inaccurate. Sorkin needs a remedial class in broadcast history. &quot;It&#39;s news 101!&quot;</p>&mdash; Max Dawson (@fymaxwell) <a href=\"https://twitter.com/fymaxwell/status/222166869665255424?ref_src=twsrc%5Etfw\">July 9, 2012</a></blockquote>\n<script async src=\"https://platform.twitter.com/widgets.js\" charset=\"utf-8\"></script>\n",
            "width": 550,
            "height": null,
            "type": "rich",
            "cache_age": "3153600000",
            "provider_name": "Twitter",
            "provider_url": "https://twitter.com",
            "version": "1.0"
        },
        {
            "url": "https://twitter.com/damianholbrook/status/222168288984174593",
            "author_name": "Damian Holbrook",
            "author_url": "https://twitter.com/damianholbrook",
            "html": "<blockquote class=\"twitter-tweet\"><p lang=\"en\" dir=\"ltr\">Is it possible that <a href=\"https://twitter.com/hashtag/Newsroom?src=hash&amp;ref_src=twsrc%5Etfw\">#Newsroom</a> is trying to tell us all something? I can never tell, the subtext is so delicate.</p>&mdash; Damian Holbrook (@damianholbrook) <a href=\"https://twitter.com/damianholbrook/status/222168288984174593?ref_src=twsrc%5Etfw\">July 9, 2012</a></blockquote>\n<script async src=\"https://platform.twitter.com/widgets.js\" charset=\"utf-8\"></script>\n",
            "width": 550,
            "height": null,
            "type": "rich",
            "cache_age": "3153600000",
            "provider_name": "Twitter",
            "provider_url": "https://twitter.com",
            "version": "1.0"
        },
        {
            "url": "https://twitter.com/mousterpiece/status/222171058940297218",
            "author_name": "Josh Spiegel",
            "author_url": "https://twitter.com/mousterpiece",
            "html": "<blockquote class=\"twitter-tweet\"><p lang=\"en\" dir=\"ltr\">If every episode of The Newsroom has Sam Waterston basically begging to fight someone, I will be mildly happy. We&#39;re 3 for 3 so far.</p>&mdash; Josh Spiegel (@mousterpiece) <a href=\"https://twitter.com/mousterpiece/status/222171058940297218?ref_src=twsrc%5Etfw\">July 9, 2012</a></blockquote>\n<script async src=\"https://platform.twitter.com/widgets.js\" charset=\"utf-8\"></script>\n",
            "width": 550,
            "height": null,
            "type": "rich",
            "cache_age": "3153600000",
            "provider_name": "Twitter",
            "provider_url": "https://twitter.com",
            "version": "1.0"
        },
        {
            "url": "https://twitter.com/mousterpiece/status/222173619005038592",
            "author_name": "Josh Spiegel",
            "author_url": "https://twitter.com/mousterpiece",
            "html": "<blockquote class=\"twitter-tweet\"><p lang=\"en\" dir=\"ltr\">What I&#39;ve learned from tonight&#39;s episode of The Newsroom: Aaron Sorkin&#39;s all-time guilty-pleasure movie is Rocky II.</p>&mdash; Josh Spiegel (@mousterpiece) <a href=\"https://twitter.com/mousterpiece/status/222173619005038592?ref_src=twsrc%5Etfw\">July 9, 2012</a></blockquote>\n<script async src=\"https://platform.twitter.com/widgets.js\" charset=\"utf-8\"></script>\n",
            "width": 550,
            "height": null,
            "type": "rich",
            "cache_age": "3153600000",
            "provider_name": "Twitter",
            "provider_url": "https://twitter.com",
            "version": "1.0"
        },
        {
            "url": "https://twitter.com/johnmoe/status/222176655991521282",
            "author_name": "John Moe",
            "author_url": "https://twitter.com/johnmoe",
            "html": "<blockquote class=\"twitter-tweet\"><p lang=\"en\" dir=\"ltr\">&quot;Who am I? I&#39;m Jack Newsroom and I BUILT this company, dammit!&quot; - scene from Newsroom</p>&mdash; John Moe (@johnmoe) <a href=\"https://twitter.com/johnmoe/status/222176655991521282?ref_src=twsrc%5Etfw\">July 9, 2012</a></blockquote>\n<script async src=\"https://platform.twitter.com/widgets.js\" charset=\"utf-8\"></script>\n",
            "width": 550,
            "height": null,
            "type": "rich",
            "cache_age": "3153600000",
            "provider_name": "Twitter",
            "provider_url": "https://twitter.com",
            "version": "1.0"
        },
        {
            "url": "https://twitter.com/fymaxwell/status/222177007843278848",
            "author_name": "Max Dawson",
            "author_url": "https://twitter.com/fymaxwell",
            "html": "<blockquote class=\"twitter-tweet\"><p lang=\"en\" dir=\"ltr\">In the last 7 days we&#39;ve seen one of the best and one of the worst examples of middlebrow catnip in TV history. <a href=\"https://twitter.com/hashtag/louie?src=hash&amp;ref_src=twsrc%5Etfw\">#louie</a> <a href=\"https://twitter.com/hashtag/newsroom?src=hash&amp;ref_src=twsrc%5Etfw\">#newsroom</a></p>&mdash; Max Dawson (@fymaxwell) <a href=\"https://twitter.com/fymaxwell/status/222177007843278848?ref_src=twsrc%5Etfw\">July 9, 2012</a></blockquote>\n<script async src=\"https://platform.twitter.com/widgets.js\" charset=\"utf-8\"></script>\n",
            "width": 550,
            "height": null,
            "type": "rich",
            "cache_age": "3153600000",
            "provider_name": "Twitter",
            "provider_url": "https://twitter.com",
            "version": "1.0"
        },
        {
            "url": "https://twitter.com/fymaxwell/status/222179489327751169",
            "author_name": "Max Dawson",
            "author_url": "https://twitter.com/fymaxwell",
            "html": "<blockquote class=\"twitter-tweet\"><p lang=\"en\" dir=\"ltr\">I need to watch something to get the Newsroom out of my mindgrapes. What is the antidote for Sorkin? Xavier Renegade Angel? Brule? Tim&amp;Eric?</p>&mdash; Max Dawson (@fymaxwell) <a href=\"https://twitter.com/fymaxwell/status/222179489327751169?ref_src=twsrc%5Etfw\">July 9, 2012</a></blockquote>\n<script async src=\"https://platform.twitter.com/widgets.js\" charset=\"utf-8\"></script>\n",
            "width": 550,
            "height": null,
            "type": "rich",
            "cache_age": "3153600000",
            "provider_name": "Twitter",
            "provider_url": "https://twitter.com",
            "version": "1.0"
        },
        {
            "url": "https://twitter.com/TVandDinners/status/222179711202242563",
            "author_name": "Carrie Raisler",
            "author_url": "https://twitter.com/TVandDinners",
            "html": "<blockquote class=\"twitter-tweet\"><p lang=\"en\" dir=\"ltr\">I am trying to watch <a href=\"https://twitter.com/hashtag/Newsroom?src=hash&amp;ref_src=twsrc%5Etfw\">#Newsroom</a> without snarking. I think it is physically impossible.</p>&mdash; Carrie Raisler (@TVandDinners) <a href=\"https://twitter.com/TVandDinners/status/222179711202242563?ref_src=twsrc%5Etfw\">July 9, 2012</a></blockquote>\n<script async src=\"https://platform.twitter.com/widgets.js\" charset=\"utf-8\"></script>\n",
            "width": 550,
            "height": null,
            "type": "rich",
            "cache_age": "3153600000",
            "provider_name": "Twitter",
            "provider_url": "https://twitter.com",
            "version": "1.0"
        },
        {
            "url": "https://twitter.com/emilyyoshida/status/222201744694837248",
            "author_name": "Emily Yoshida",
            "author_url": "https://twitter.com/emilyyoshida",
            "html": "<blockquote class=\"twitter-tweet\"><p lang=\"en\" dir=\"ltr\">Women on <a href=\"https://twitter.com/hashtag/Newsroom?src=hash&amp;ref_src=twsrc%5Etfw\">#Newsroom</a> A) work for Will McAvoy &amp; are crazy B) Drink pink drinks in midtown or C) can be neurosurgeons, if the joke calls for it</p>&mdash; Emily Yoshida (@emilyyoshida) <a href=\"https://twitter.com/emilyyoshida/status/222201744694837248?ref_src=twsrc%5Etfw\">July 9, 2012</a></blockquote>\n<script async src=\"https://platform.twitter.com/widgets.js\" charset=\"utf-8\"></script>\n",
            "width": 550,
            "height": null,
            "type": "rich",
            "cache_age": "3153600000",
            "provider_name": "Twitter",
            "provider_url": "https://twitter.com",
            "version": "1.0"
        },
        {
            "url": "https://twitter.com/rural_juror/status/222207322884276224",
            "author_name": "Tim",
            "author_url": "https://twitter.com/rural_juror",
            "html": "<blockquote class=\"twitter-tweet\"><p lang=\"en\" dir=\"ltr\">Can we get a show of Jane Fonda &amp; Sam Waterston arguing in Sorkin-ian dialogue for an hour each week? Cause I would watch that. <a href=\"https://twitter.com/hashtag/TheNewsroom?src=hash&amp;ref_src=twsrc%5Etfw\">#TheNewsroom</a></p>&mdash; Tim (@rural_juror) <a href=\"https://twitter.com/rural_juror/status/222207322884276224?ref_src=twsrc%5Etfw\">July 9, 2012</a></blockquote>\n<script async src=\"https://platform.twitter.com/widgets.js\" charset=\"utf-8\"></script>\n",
            "width": 550,
            "height": null,
            "type": "rich",
            "cache_age": "3153600000",
            "provider_name": "Twitter",
            "provider_url": "https://twitter.com",
            "version": "1.0"
        },
        {
            "url": "https://twitter.com/wilzmak/status/222214836967313409",
            "author_name": "Wil Zmak",
            "author_url": "https://twitter.com/wilzmak",
            "html": "<blockquote class=\"twitter-tweet\"><p lang=\"en\" dir=\"ltr\">The gals take it on the chin again in <a href=\"https://twitter.com/hashtag/TheNewsroom?src=hash&amp;ref_src=twsrc%5Etfw\">#TheNewsroom</a>. Panic attacks! Next Allison Pill&#39;s uterus comes out at night and shoplifts at Bergdorfs.</p>&mdash; Wil Zmak (@wilzmak) <a href=\"https://twitter.com/wilzmak/status/222214836967313409?ref_src=twsrc%5Etfw\">July 9, 2012</a></blockquote>\n<script async src=\"https://platform.twitter.com/widgets.js\" charset=\"utf-8\"></script>\n",
            "width": 550,
            "height": null,
            "type": "rich",
            "cache_age": "3153600000",
            "provider_name": "Twitter",
            "provider_url": "https://twitter.com",
            "version": "1.0"
        },
        {
            "url": "https://twitter.com/Memles/status/222219886385053696",
            "author_name": "Myles McNutt",
            "author_url": "https://twitter.com/Memles",
            "html": "<blockquote class=\"twitter-tweet\"><p lang=\"en\" dir=\"ltr\">At least this week&#39;s Newsroom was structurally interesting; it was also a complete and total mess, but in new and exciting ways!</p>&mdash; Myles McNutt (@Memles) <a href=\"https://twitter.com/Memles/status/222219886385053696?ref_src=twsrc%5Etfw\">July 9, 2012</a></blockquote>\n<script async src=\"https://platform.twitter.com/widgets.js\" charset=\"utf-8\"></script>\n",
            "width": 550,
            "height": null,
            "type": "rich",
            "cache_age": "3153600000",
            "provider_name": "Twitter",
            "provider_url": "https://twitter.com",
            "version": "1.0"
        },
        {
            "url": "https://twitter.com/Memles/status/222225084880924672",
            "author_name": "Myles McNutt",
            "author_url": "https://twitter.com/Memles",
            "html": "<blockquote class=\"twitter-tweet\"><p lang=\"en\" dir=\"ltr\">One last Newsroom nitpick before I go to sleep: pretty sure the reference to Scott Walker wanting to bust unions was fairly anachronistic.</p>&mdash; Myles McNutt (@Memles) <a href=\"https://twitter.com/Memles/status/222225084880924672?ref_src=twsrc%5Etfw\">July 9, 2012</a></blockquote>\n<script async src=\"https://platform.twitter.com/widgets.js\" charset=\"utf-8\"></script>\n",
            "width": 550,
            "height": null,
            "type": "rich",
            "cache_age": "3153600000",
            "provider_name": "Twitter",
            "provider_url": "https://twitter.com",
            "version": "1.0"
        },
        {
            "url": "https://twitter.com/RowanKaiser/status/222226711125831680",
            "author_name": "Rowan Kaiser",
            "author_url": "https://twitter.com/RowanKaiser",
            "html": "<blockquote class=\"twitter-tweet\"><p lang=\"en\" dir=\"ltr\"><a href=\"https://twitter.com/Memles?ref_src=twsrc%5Etfw\">@Memles</a> You say anachronistic, I say foreshadowing in proper serialized fashion.</p>&mdash; Rowan Kaiser (@RowanKaiser) <a href=\"https://twitter.com/RowanKaiser/status/222226711125831680?ref_src=twsrc%5Etfw\">July 9, 2012</a></blockquote>\n<script async src=\"https://platform.twitter.com/widgets.js\" charset=\"utf-8\"></script>\n",
            "width": 550,
            "height": null,
            "type": "rich",
            "cache_age": "3153600000",
            "provider_name": "Twitter",
            "provider_url": "https://twitter.com",
            "version": "1.0"
        },
        {
            "url": "https://twitter.com/Memles/status/222226851022643200",
            "author_name": "Myles McNutt",
            "author_url": "https://twitter.com/Memles",
            "html": "<blockquote class=\"twitter-tweet\"><p lang=\"en\" dir=\"ltr\">Sorkin has ruined television for the rest of us. RT <a href=\"https://twitter.com/RowanKaiser?ref_src=twsrc%5Etfw\">@RowanKaiser</a> You say anachronistic, I say foreshadowing in proper serialized fashion.</p>&mdash; Myles McNutt (@Memles) <a href=\"https://twitter.com/Memles/status/222226851022643200?ref_src=twsrc%5Etfw\">July 9, 2012</a></blockquote>\n<script async src=\"https://platform.twitter.com/widgets.js\" charset=\"utf-8\"></script>\n",
            "width": 550,
            "height": null,
            "type": "rich",
            "cache_age": "3153600000",
            "provider_name": "Twitter",
            "provider_url": "https://twitter.com",
            "version": "1.0"
        },
        {
            "url": "https://twitter.com/Snoodit/status/222231209026138112",
            "author_name": "Lesley Goldberg",
            "author_url": "https://twitter.com/Snoodit",
            "html": "<blockquote class=\"twitter-tweet\"><p lang=\"en\" dir=\"ltr\">Just watched Sam Waterston say &quot;douchebaggery 101.&quot; Awesome. <a href=\"https://twitter.com/hashtag/Newsroom?src=hash&amp;ref_src=twsrc%5Etfw\">#Newsroom</a></p>&mdash; Lesley Goldberg (@Snoodit) <a href=\"https://twitter.com/Snoodit/status/222231209026138112?ref_src=twsrc%5Etfw\">July 9, 2012</a></blockquote>\n<script async src=\"https://platform.twitter.com/widgets.js\" charset=\"utf-8\"></script>\n",
            "width": 550,
            "height": null,
            "type": "rich",
            "cache_age": "3153600000",
            "provider_name": "Twitter",
            "provider_url": "https://twitter.com",
            "version": "1.0"
        },
        {
            "url": "https://twitter.com/arrabin56/status/222307062338699264",
            "author_name": "(((Andrew Rabin)))📎",
            "author_url": "https://twitter.com/arrabin56",
            "html": "<blockquote class=\"twitter-tweet\"><p lang=\"en\" dir=\"ltr\">Has anybody talked about the Charlie Crist mistake on <a href=\"https://twitter.com/hashtag/Newsroom?src=hash&amp;ref_src=twsrc%5Etfw\">#Newsroom</a>? Cuz as much as I enjoyed the episode, that&#39;s a bad mistake.</p>&mdash; (((Andrew Rabin)))📎 (@arrabin56) <a href=\"https://twitter.com/arrabin56/status/222307062338699264?ref_src=twsrc%5Etfw\">July 9, 2012</a></blockquote>\n<script async src=\"https://platform.twitter.com/widgets.js\" charset=\"utf-8\"></script>\n",
            "width": 550,
            "height": null,
            "type": "rich",
            "cache_age": "3153600000",
            "provider_name": "Twitter",
            "provider_url": "https://twitter.com",
            "version": "1.0"
        },
        {
            "url": "https://twitter.com/AmandaAnnKlein/status/222332945183162369",
            "author_name": "Moved on Her Like a Bitch but Couldn't Get There",
            "author_url": "https://twitter.com/AmandaAnnKlein",
            "html": "<blockquote class=\"twitter-tweet\"><p lang=\"en\" dir=\"ltr\">NEWSROOM is about journalists who travel 2 the future then use this knowledge 2 make folks in the past feel stupid 4 not knowing the future.</p>&mdash; Moved on Her Like a Bitch but Couldn&#39;t Get There (@AmandaAnnKlein) <a href=\"https://twitter.com/AmandaAnnKlein/status/222332945183162369?ref_src=twsrc%5Etfw\">July 9, 2012</a></blockquote>\n<script async src=\"https://platform.twitter.com/widgets.js\" charset=\"utf-8\"></script>\n",
            "width": 550,
            "height": null,
            "type": "rich",
            "cache_age": "3153600000",
            "provider_name": "Twitter",
            "provider_url": "https://twitter.com",
            "version": "1.0"
        },
        {
            "url": "https://twitter.com/TheTweetOfGod/status/222314548093399041",
            "author_name": "God",
            "author_url": "https://twitter.com/TheTweetOfGod",
            "html": "<blockquote class=\"twitter-tweet\"><p lang=\"en\" dir=\"ltr\">Satire is a plunger that gets blamed for all the shit it pulls up.</p>&mdash; God (@TheTweetOfGod) <a href=\"https://twitter.com/TheTweetOfGod/status/222314548093399041?ref_src=twsrc%5Etfw\">July 9, 2012</a></blockquote>\n<script async src=\"https://platform.twitter.com/widgets.js\" charset=\"utf-8\"></script>\n",
            "width": 550,
            "height": null,
            "type": "rich",
            "cache_age": "3153600000",
            "provider_name": "Twitter",
            "provider_url": "https://twitter.com",
            "version": "1.0"
        },
        {
            "url": "https://twitter.com/jasonmustian/status/222318586352504832",
            "author_name": "Jason Mustian",
            "author_url": "https://twitter.com/jasonmustian",
            "html": "<blockquote class=\"twitter-tweet\"><p lang=\"en\" dir=\"ltr\">The greatest trick the devil ever pulled was convincing the world they&#39;d see something cool in the &quot;Unrated Version.&quot;</p>&mdash; Jason Mustian (@jasonmustian) <a href=\"https://twitter.com/jasonmustian/status/222318586352504832?ref_src=twsrc%5Etfw\">July 9, 2012</a></blockquote>\n<script async src=\"https://platform.twitter.com/widgets.js\" charset=\"utf-8\"></script>\n",
            "width": 550,
            "height": null,
            "type": "rich",
            "cache_age": "3153600000",
            "provider_name": "Twitter",
            "provider_url": "https://twitter.com",
            "version": "1.0"
        }
    ],
    "lost": [
        "http://twitter.com/JoseMolinaTV/status/222219748593766400",
        "http://twitter.com/CaptainAnnoying/status/222153610153295872",
        "http://twitter.com/DomKing456/status/222156902115717120",
        "http://twitter.com/ErnieLies/status/222164671585730560"
    ],
    "missing": []
}